nexus/__init__.py
nexus/cli.py
nexus/core/audit.py
nexus/core/config.py
nexus/core/plugin_loader.py
nexus/core/storage.py
nexus/modules/cryptography/__init__.py
nexus/modules/cryptography/service.py
nexus/modules/enumeration/__init__.py
nexus/modules/enumeration/service.py
nexus/modules/log_analysis/__init__.py
nexus/modules/log_analysis/service.py
nexus/modules/osint/__init__.py
nexus/modules/osint/service.py
nexus_tool-0.1.3.dist-info/METADATA
nexus_tool-0.1.3.dist-info/WHEEL
nexus_tool-0.1.3.dist-info/entry_points.txt
nexus_tool-0.1.3.dist-info/licenses/LICENSE
nexus_tool-0.1.3.dist-info/RECORD
