Metadata-Version: 2.4
Name: nexus-tool
Version: 0.1.3
Summary: Local-first terminal toolkit for cryptography, OSINT, logs, enumeration
License-File: LICENSE
Requires-Python: >=3.11
Requires-Dist: click>=8.1
Requires-Dist: duckdb>=1.0
Requires-Dist: pandas>=2.2
Requires-Dist: pillow>=10.0
Requires-Dist: pyarrow>=16.0
